sql_status/__init__.py
sql_status/__main__.py
sql_status/unpack.py
sql_status/gia3/db_import_ready.xlsx
sql_status/gia3/zaprosi.sql
sql_status/gia3/src/admin_window.py
sql_status/gia3/src/database.py
sql_status/gia3/src/login_window.py
sql_status/gia3/src/logo.ico
sql_status/gia3/src/main.py
sql_status/gia3/src/manager_window.py
sql_status/gia3/src/partner_window.py
sql_status/gia3/src/windows/create_product_window.py
sql_status/gia3/src/windows/orders_tab.py
sql_status/gia3/src/windows/partners_tab.py
sql_status/gia3/src/windows/products_tab.py
sql_status/gia3/src/windows/users_tab.py
sql_status/gia4/normalized_database.xlsx
sql_status/gia4/zaprosi.sql
sql_status/gia4/src/admin_window.py
sql_status/gia4/src/database.py
sql_status/gia4/src/login_window.py
sql_status/gia4/src/logo.ico
sql_status/gia4/src/main.py
sql_status/gia4/src/manager_window.py
sql_status/gia4/src/worker_window.py
sql_status/gia4/src/windows/create_product_window.py
sql_status/gia4/src/windows/materials_tab.py
sql_status/gia4/src/windows/product_workshops_dialog.py
sql_status/gia4/src/windows/products_tab.py
sql_status/gia4/src/windows/styles.py
sql_status/gia4/src/windows/ui_utils.py
sql_status/gia4/src/windows/users_tab.py
sql_status/gia4/src/windows/workshops_tab.py
sql_status/gia5/import_ready.xlsx
sql_status/gia5/zaprosi.sql
sql_status/gia5/src/admin_window.py
sql_status/gia5/src/database.py
sql_status/gia5/src/login_window.py
sql_status/gia5/src/logo.ico
sql_status/gia5/src/main.py
sql_status/gia5/src/manager_window.py
sql_status/gia5/src/worker_window.py
sql_status/gia5/src/windows/materials_tab.py
sql_status/gia5/src/windows/product_materials_dialog.py
sql_status/gia5/src/windows/products_tab.py
sql_status/gia5/src/windows/styles.py
sql_status/gia5/src/windows/ui_utils.py
sql_status/gia5/src/windows/users_tab.py
sql_status-0.2.4.dist-info/METADATA
sql_status-0.2.4.dist-info/WHEEL
sql_status-0.2.4.dist-info/entry_points.txt
sql_status-0.2.4.dist-info/top_level.txt
sql_status-0.2.4.dist-info/RECORD
